cmflumped/__init__.py
cmflumped/__main__.py
cmflumped/basemodel.py
cmflumped/commands.py
cmflumped/dataprovider.py
cmflumped/spotpy_helper.py
cmflumped/doctools/__init__.py
cmflumped/doctools/conf.py
cmflumped/doctools/doc_base.py
cmflumped/doctools/make_doc.py
cmflumped/doctools/result.py
cmflumped/gui/__init__.py
cmflumped/gui/fluxogram.py
cmflumped/gui/gui.py
cmflumped-2025.1.16.dist-info/LICENSE
cmflumped-2025.1.16.dist-info/METADATA
cmflumped-2025.1.16.dist-info/WHEEL
cmflumped-2025.1.16.dist-info/entry_points.txt
cmflumped-2025.1.16.dist-info/top_level.txt
cmflumped-2025.1.16.dist-info/RECORD
